<?xml version="1.0" encoding="UTF-8" standalone="yes"?><imgdir name="FreeCouponStock.img"><int name="0" value="10100279"/><int name="1" value="10100443"/><int name="2" value="10100451"/><int name="3" value="10100367"/><int name="4" value="10100178"/><int name="5" value="10100274"/><int name="6" value="10100275"/><int name="7" value="10100444"/><int name="8" value="10100182"/><int name="9" value="10100183"/><int name="10" value="10100184"/><int name="11" value="10100185"/><int name="12" value="10100186"/><int name="13" value="10100187"/><int name="14" value="10100188"/><int name="15" value="10100189"/><int name="16" value="10100190"/><int name="17" value="10100191"/><int name="18" value="10100192"/><int name="19" value="10100193"/><int name="20" value="10100194"/><int name="21" value="10100285"/><int name="22" value="10100036"/><int name="23" value="10100286"/><int name="24" value="10100197"/><int name="25" value="10100273"/><int name="26" value="10100376"/><int name="27" value="10100287"/><int name="28" value="10100201"/><int name="29" value="10100371"/><int name="30" value="10100448"/><int name="31" value="10100372"/><int name="32" value="10100269"/><int name="33" value="10100270"/><int name="34" value="10100271"/><int name="35" value="10100450"/><int name="36" value="10100209"/><int name="37" value="10100142"/><int name="38" value="10100211"/><int name="39" value="10100212"/><int name="40" value="10100213"/><int name="41" value="10100214"/><int name="42" value="10100215"/><int name="43" value="10100216"/><int name="44" value="10100411"/><int name="45" value="10100218"/><int name="46" value="10100379"/><int name="47" value="10100395"/><int name="48" value="10100354"/><int name="49" value="10100222"/><int name="50" value="10100224"/><int name="51" value="10100225"/><int name="52" value="10100226"/><int name="53" value="10100227"/><int name="54" value="10100440"/><int name="55" value="10100229"/><int name="56" value="10100230"/><int name="57" value="10100381"/><int name="58" value="10100150"/><int name="59" value="10100277"/><int name="60" value="10100278"/><int name="61" value="10100404"/><int name="62" value="10100400"/><int name="63" value="10100237"/><int name="64" value="10100238"/><int name="65" value="10100441"/><int name="66" value="10100293"/><int name="67" value="10100241"/><int name="68" value="10100242"/><int name="69" value="10100243"/><int name="70" value="10100244"/><int name="71" value="10100384"/><int name="72" value="10100181"/><int name="73" value="10100247"/><int name="74" value="10100248"/><int name="75" value="10100282"/><int name="76" value="10100385"/><int name="77" value="10100251"/><int name="78" value="10100252"/><int name="79" value="10100253"/><int name="80" value="10100254"/><int name="81" value="10100255"/><int name="82" value="10100256"/><int name="83" value="10100257"/><int name="84" value="10100079"/><int name="85" value="10100080"/><int name="86" value="10100258"/><int name="87" value="10100259"/><int name="88" value="10100260"/><int name="89" value="10100261"/><int name="90" value="10100262"/><int name="91" value="10100263"/><int name="92" value="10100387"/><int name="93" value="10100265"/><int name="94" value="10100296"/><int name="95" value="10100267"/><int name="96" value="10100445"/><int name="97" value="10100005"/><int name="98" value="10100298"/><int name="99" value="10100366"/><int name="100" value="10100299"/><int name="101" value="10100300"/><int name="102" value="10100368"/><int name="103" value="10100301"/><int name="104" value="10100446"/><int name="105" value="10100369"/><int name="106" value="10100304"/><int name="107" value="10100305"/><int name="108" value="10100306"/><int name="109" value="10100307"/><int name="110" value="10100308"/><int name="111" value="10100309"/><int name="112" value="10100144"/><int name="113" value="10100310"/><int name="114" value="10100311"/><int name="115" value="10100312"/><int name="116" value="10100197"/><int name="117" value="10100313"/><int name="118" value="10100453"/><int name="119" value="10100452"/><int name="120" value="10100409"/><int name="121" value="10100410"/><int name="122" value="10100447"/><int name="123" value="10100393"/><int name="124" value="10100439"/><int name="125" value="10100223"/><int name="126" value="10100449"/><int name="127" value="10100318"/><int name="128" value="10100319"/><int name="129" value="10100370"/><int name="130" value="10100111"/><int name="131" value="10100321"/><int name="132" value="10100322"/><int name="133" value="10100039"/><int name="134" value="10100394"/><int name="135" value="10100396"/><int name="136" value="10100324"/><int name="137" value="10100325"/><int name="138" value="10100326"/><int name="139" value="10100397"/><int name="140" value="10100106"/><int name="141" value="10100398"/><int name="142" value="10100328"/><int name="143" value="10100114"/><int name="144" value="10100074"/><int name="145" value="10100382"/><int name="146" value="10100330"/><int name="147" value="10100331"/><int name="148" value="10100332"/><int name="149" value="10100333"/><int name="150" value="10100334"/><int name="151" value="10100238"/><int name="152" value="10100069"/><int name="153" value="10100068"/><int name="154" value="10100163"/><int name="155" value="10100157"/><int name="156" value="10100167"/><int name="157" value="10100335"/><int name="158" value="10100336"/><int name="159" value="10100386"/><int name="160" value="10100173"/><int name="161" value="10100403"/><int name="162" value="10100340"/><int name="163" value="10100151"/><int name="164" value="10100341"/><int name="165" value="10100342"/><int name="166" value="10100254"/><int name="167" value="10100343"/><int name="168" value="10100153"/><int name="169" value="10100401"/><int name="170" value="10100390"/><int name="171" value="10100345"/><int name="172" value="10100257"/><int name="173" value="10100346"/><int name="174" value="10100347"/><int name="175" value="10100348"/><int name="176" value="10100021"/><int name="177" value="10100350"/><int name="178" value="10100351"/><int name="179" value="10100352"/><int name="180" value="10100353"/><int name="181" value="10100388"/><int name="182" value="10100355"/><int name="183" value="10100356"/><int name="184" value="10100389"/><int name="185" value="10100358"/><int name="186" value="10100359"/><int name="187" value="10100282"/><int name="188" value="10100360"/><int name="189" value="10100361"/><int name="190" value="10100263"/><int name="191" value="10100121"/><int name="192" value="10100362"/><int name="193" value="10100363"/><int name="194" value="10100364"/><int name="195" value="10100365"/><int name="196" value="10100383"/><int name="197" value="10100392"/><int name="198" value="10100442"/><int name="199" value="10100174"/><int name="200" value="10100454"/></imgdir>